[{"__type__":"cc.SpriteFrame","content":{"name":"Armature_newAnimation_17","texture":"18e0a839b","rect":[420,411,275,263],"offset":[1.5,3],"originalSize":[278,285]}},[{"__type__":"cc.Prefab","_name":"fish34","data":{"__id__":1},"asyncLoadAssets":false},{"__type__":"cc.Node","_name":"fish34","_children":[{"__id__":2},{"__id__":3},{"__id__":4}],"_components":[{"__type__":"cc.Animation","node":{"__id__":1},"_clips":[{"__uuid__":"7b6XUQcOpKraUR1umGhH7j"},{"__uuid__":"4bnuEmEQ1Hf7xD+U3heZgl"}]},{"__type__":"cc.BoxCollider","node":{"__id__":1},"_offset":{"__type__":"cc.Vec2","x":-7},"_size":{"__type__":"cc.Size","width":215,"height":197}},{"__type__":"41aa4RANDlBg77lBFLsc9ft","node":{"__id__":1},"lockPos":{"__id__":4}},{"__type__":"cc.Button","node":{"__id__":1},"clickEvents":[{"__type__":"cc.ClickEvent","target":{"__id__":1},"component":"Fish","handler":"onLocked"}],"_N$target":{"__id__":1}}],"_prefab":{"__type__":"cc.PrefabInfo","root":{"__id__":1},"asset":{"__uuid__":"2c6OEzHoJPP4VphBMI9O+5"},"fileId":"8b399QkBaRKjYlxC8hrfkc+"},"_contentSize":{"__type__":"cc.Size","width":200,"height":200},"groupIndex":1},{"__type__":"cc.Node","_name":"fish_402","_parent":{"__id__":1},"_components":[{"__type__":"cc.Sprite","node":{"__id__":2},"_spriteFrame":{"__uuid__":"899+Nr4oJFJoRIGQxwGEdQ"}}],"_prefab":{"__type__":"cc.PrefabInfo","root":{"__id__":1},"asset":{"__uuid__":"2c6OEzHoJPP4VphBMI9O+5"},"fileId":"7ddd45ZS9VPF4eOQyRhas5y"},"_anchorPoint":{"__type__":"cc.Vec2","x":0.5,"y":0.507168458781362},"_contentSize":{"__type__":"cc.Size","width":290,"height":279},"_rotationX":86.8570565000009,"_rotationY":86.8570565000009,"_position":{"__type__":"cc.Vec2","x":-1,"y":-1}},{"__type__":"cc.Node","_name":"Armature_newAnimation_12","_parent":{"__id__":1},"_components":[{"__type__":"cc.Sprite","node":{"__id__":3},"_spriteFrame":{"__uuid__":"2aiE50G/1NtbxFRgMBjf3X"}}],"_prefab":{"__type__":"cc.PrefabInfo","root":{"__id__":1},"asset":{"__uuid__":"2c6OEzHoJPP4VphBMI9O+5"},"fileId":"fb373MJjHhE5Y0NbmcKwrDA"},"_anchorPoint":{"__type__":"cc.Vec2","x":0.6086956521739135,"y":0.4882352941176471},"_contentSize":{"__type__":"cc.Size","width":275,"height":263},"_position":{"__type__":"cc.Vec2","x":-7,"y":5}},{"__type__":"cc.Node","_name":"lockPos","_parent":{"__id__":1},"_active":false,"_components":[{"__type__":"cc.Sprite","node":{"__id__":4},"_spriteFrame":{"__uuid__":"69yvFzPQhPnYuMDb+xILtT"}}],"_prefab":{"__type__":"cc.PrefabInfo","root":{"__id__":1},"asset":{"__uuid__":"2c6OEzHoJPP4VphBMI9O+5"},"fileId":"f8a64yBgYxMp4nCiiX6vpdD"},"_contentSize":{"__type__":"cc.Size","width":90,"height":87},"_scaleX":1.0397309999995996,"_scaleY":1.0397309999995996}],{"__type__":"cc.SpriteFrame","content":{"name":"lockIcon","texture":"14aea2c76","rect":[165,930,90,87],"offset":[0,0],"originalSize":[90,87]}},{"__type__":"cc.SpriteFrame","content":{"name":"fish_402","texture":"18e0a839b","rect":[2,263,290,279],"offset":[0,0],"originalSize":[290,279]}}]