[{"__type__":"cc.SpriteFrame","content":{"name":"fish_207","texture":"178824ef5","rect":[460,948,145,72],"offset":[-0.5,0],"originalSize":[180,120]}},{"__type__":"cc.SpriteFrame","content":{"name":"fish_209","texture":"178824ef5","rect":[309,948,147,73],"offset":[0.5,0.5],"originalSize":[180,120]}},{"__type__":"cc.SpriteFrame","content":{"name":"fish_203","texture":"1570b8785","rect":[206,813,147,64],"offset":[-0.5,0],"originalSize":[180,120],"rotated":1}},{"__type__":"cc.SpriteFrame","content":{"name":"fish_219","texture":"18e0a839b","rect":[915,569,154,72],"offset":[0,0],"originalSize":[180,120],"rotated":1}},{"__type__":"cc.SpriteFrame","content":{"name":"fish_211","texture":"1570b8785","rect":[323,952,147,70],"offset":[-0.5,0],"originalSize":[180,120]}},{"__type__":"cc.SpriteFrame","content":{"name":"fish_217","texture":"1570b8785","rect":[915,2,155,67],"offset":[-0.5,-0.5],"originalSize":[180,120],"rotated":1}},{"__type__":"cc.SpriteFrame","content":{"name":"fish_199","texture":"1570b8785","rect":[281,272,152,71],"offset":[0,0.5],"originalSize":[180,120]}},{"__type__":"cc.SpriteFrame","content":{"name":"fish_221","texture":"18e0a839b","rect":[915,411,154,73],"offset":[0,0.5],"originalSize":[180,120],"rotated":1}},{"__type__":"cc.SpriteFrame","content":{"name":"fish_213","texture":"1570b8785","rect":[206,658,151,66],"offset":[-1.5,0],"originalSize":[180,120],"rotated":1}},{"__type__":"cc.AnimationClip","_name":"fish10move","_duration":1.13,"sample":8,"wrapMode":2,"curveData":{"comps":{"cc.Sprite":{"spriteFrame":[{"frame":0,"value":{"__uuid__":"c8BO9K0qJG7rT2kNKlDBxZ"}},{"frame":0.125,"value":{"__uuid__":"674FTetOdNmJBHaVS8T9Um"}},{"frame":0.25,"value":{"__uuid__":"2acoTds8NJo7vC3bpUXLS1"}},{"frame":0.375,"value":{"__uuid__":"39mz+YXF9Lgp2WWjr3tMrL"}},{"frame":0.5,"value":{"__uuid__":"81kaKTmQxLmL9iFCiTAbpc"}},{"frame":0.625,"value":{"__uuid__":"edt/o0ixdAIatD9IoBuCVo"}},{"frame":0.75,"value":{"__uuid__":"9e+KdSNhhLQKzEn8hMKgD+"}},{"frame":0.875,"value":{"__uuid__":"6ab6aFiIpIorxI5V0epuBh"}},{"frame":1,"value":{"__uuid__":"d7M+fLdKNENpasUi/Te2R7"}}]}},"paths":{"lockPos":{"props":{"scaleX":[{"frame":0,"value":1},{"frame":0.125,"value":1.1},{"frame":0.25,"value":1},{"frame":0.375,"value":1.1},{"frame":0.5,"value":1},{"frame":0.625,"value":1.1},{"frame":0.75,"value":1},{"frame":0.875,"value":1.1},{"frame":1,"value":1}],"scaleY":[{"frame":0,"value":1},{"frame":0.125,"value":1.1},{"frame":0.25,"value":1},{"frame":0.375,"value":1.1},{"frame":0.5,"value":1},{"frame":0.625,"value":1.1},{"frame":0.75,"value":1},{"frame":0.875,"value":1.1},{"frame":1,"value":1}]}}}}}]