[{"__type__":"cc.SpriteFrame","content":{"name":"rankItemBg","texture":"12865bb7","rect":[842,684,256,84],"offset":[0,0],"originalSize":[256,84],"rotated":1,"capInsets":[15,15,224,19]}},{"__type__":"cc.SpriteFrame","content":{"name":"default_btn_disabled","texture":"71VhFCTINJM6/Ky3oX9nBT","rect":[0,0,40,40],"offset":[0,0],"originalSize":[40,40],"capInsets":[15,7,15,9]}},{"__type__":"cc.SpriteFrame","content":{"name":"emil_unopen","texture":"137e29ded","rect":[86,306,75,68],"offset":[0,0],"originalSize":[75,68]}},{"__type__":"cc.SpriteFrame","content":{"name":"emil_open","texture":"12865bb7","rect":[570,696,72,62],"offset":[0,0],"originalSize":[72,62],"rotated":1}},[{"__type__":"cc.Prefab","_name":"emailItem","data":{"__id__":1},"asyncLoadAssets":false},{"__type__":"cc.Node","_name":"emailItem","_children":[{"__id__":2},{"__id__":3},{"__id__":4},{"__id__":5},{"__id__":7}],"_components":[{"__type__":"cc.Sprite","node":{"__id__":1},"_spriteFrame":{"__uuid__":"0b2mJW3EtDDI8/leFZFxlo"},"_type":1,"_sizeMode":0}],"_prefab":{"__type__":"cc.PrefabInfo","root":{"__id__":1},"asset":{"__uuid__":"b4a7SA5XNNRKz93p7VvlYs"},"fileId":"c640cIx5rNLf4uATft3Vorc"},"_contentSize":{"__type__":"cc.Size","width":900,"height":84},"_position":{"__type__":"cc.Vec2","y":-52}},{"__type__":"cc.Node","_name":"emil_unopen","_parent":{"__id__":1},"_components":[{"__type__":"cc.Sprite","node":{"__id__":2},"_spriteFrame":{"__uuid__":"761xx6MR9O+7yxCNoV0/f9"}}],"_prefab":{"__type__":"cc.PrefabInfo","root":{"__id__":1},"asset":{"__uuid__":"b4a7SA5XNNRKz93p7VvlYs"},"fileId":"b14203T3w9Fh5ugHZkgBUrx"},"_contentSize":{"__type__":"cc.Size","width":75,"height":68},"_position":{"__type__":"cc.Vec2","x":-400}},{"__type__":"cc.Node","_name":"emil_open","_parent":{"__id__":1},"_active":false,"_components":[{"__type__":"cc.Sprite","node":{"__id__":3},"_spriteFrame":{"__uuid__":"7bXRI46xVJ3a7dpFYlM0l5"}}],"_prefab":{"__type__":"cc.PrefabInfo","root":{"__id__":1},"asset":{"__uuid__":"b4a7SA5XNNRKz93p7VvlYs"},"fileId":"4cf475pq0tJ9qZ9XiT6lwlU"},"_contentSize":{"__type__":"cc.Size","width":72,"height":62},"_position":{"__type__":"cc.Vec2","x":-400}},{"__type__":"cc.Node","_name":"New Label","_parent":{"__id__":1},"_components":[{"__type__":"cc.Label","node":{"__id__":4},"_useOriginalSize":false,"_N$string":"欢迎来到《捕鱼大亨》","_N$verticalAlign":1,"_N$overflow":2}],"_prefab":{"__type__":"cc.PrefabInfo","root":{"__id__":1},"asset":{"__uuid__":"b4a7SA5XNNRKz93p7VvlYs"},"fileId":"751cdrTbIpJEIiHpX6M69r5"},"_color":{"__type__":"cc.Color","r":6,"g":101,"b":221},"_anchorPoint":{"__type__":"cc.Vec2","y":0.5},"_contentSize":{"__type__":"cc.Size","width":541,"height":40},"_position":{"__type__":"cc.Vec2","x":-340}},{"__type__":"cc.Node","_name":"btn_read","_parent":{"__id__":1},"_children":[{"__id__":6}],"_components":[{"__type__":"cc.Sprite","node":{"__id__":5},"_spriteFrame":{"__uuid__":"46QQxGZ+pAEZyAO9CyaffF"},"_type":1,"_sizeMode":0},{"__type__":"cc.Button","node":{"__id__":5},"transition":3,"pressedColor":{"__type__":"cc.Color","r":255,"g":255,"b":255},"zoomScale":0.9,"pressedSprite":{"__uuid__":"e97GVMl6JHh5Ml5qEDdSGa"},"hoverSprite":{"__uuid__":"e97GVMl6JHh5Ml5qEDdSGa"},"_N$normalColor":{"__type__":"cc.Color","r":255,"g":255,"b":255},"_N$disabledColor":{"__type__":"cc.Color","r":255,"g":255,"b":255},"_N$normalSprite":{"__uuid__":"46QQxGZ+pAEZyAO9CyaffF"},"_N$disabledSprite":{"__uuid__":"29FYIk+N1GYaeWH/q1NxQO"},"_N$target":{"__id__":5}}],"_prefab":{"__type__":"cc.PrefabInfo","root":{"__id__":1},"asset":{"__uuid__":"b4a7SA5XNNRKz93p7VvlYs"},"fileId":"4c8ecUkYuhEwIB9K6FRYMCt"},"_contentSize":{"__type__":"cc.Size","width":120,"height":60},"_position":{"__type__":"cc.Vec2","x":347}},{"__type__":"cc.Node","_name":"Label","_parent":{"__id__":5},"_components":[{"__type__":"cc.Label","node":{"__id__":6},"_useOriginalSize":false,"_actualFontSize":20,"_fontSize":20,"_enableWrapText":false,"_N$string":"阅读","_N$horizontalAlign":1,"_N$verticalAlign":1,"_N$overflow":1}],"_prefab":{"__type__":"cc.PrefabInfo","root":{"__id__":1},"asset":{"__uuid__":"b4a7SA5XNNRKz93p7VvlYs"},"fileId":"69feamKE6ZI9qCn1Sf7kAba"},"_contentSize":{"__type__":"cc.Size","width":100,"height":40}},{"__type__":"cc.Node","_name":"btn_delete","_parent":{"__id__":1},"_children":[{"__id__":8}],"_active":false,"_components":[{"__type__":"cc.Sprite","node":{"__id__":7},"_spriteFrame":{"__uuid__":"effRqn9K5GBrXmeQog4/qe"},"_type":1,"_sizeMode":0},{"__type__":"cc.Button","node":{"__id__":7},"transition":2,"pressedColor":{"__type__":"cc.Color","r":255,"g":255,"b":255},"pressedSprite":{"__uuid__":"e97GVMl6JHh5Ml5qEDdSGa"},"hoverSprite":{"__uuid__":"e97GVMl6JHh5Ml5qEDdSGa"},"_N$normalColor":{"__type__":"cc.Color","r":255,"g":255,"b":255},"_N$disabledColor":{"__type__":"cc.Color","r":255,"g":255,"b":255},"_N$disabledSprite":{"__uuid__":"29FYIk+N1GYaeWH/q1NxQO"},"_N$target":{"__id__":7}}],"_prefab":{"__type__":"cc.PrefabInfo","root":{"__id__":1},"asset":{"__uuid__":"b4a7SA5XNNRKz93p7VvlYs"},"fileId":"501572OXNxDHYmlqMPDtRZM"},"_contentSize":{"__type__":"cc.Size","width":120,"height":60},"_position":{"__type__":"cc.Vec2","x":347}},{"__type__":"cc.Node","_name":"Label","_parent":{"__id__":7},"_components":[{"__type__":"cc.Label","node":{"__id__":8},"_useOriginalSize":false,"_actualFontSize":20,"_fontSize":20,"_enableWrapText":false,"_N$string":"删除","_N$horizontalAlign":1,"_N$verticalAlign":1,"_N$overflow":1}],"_prefab":{"__type__":"cc.PrefabInfo","root":{"__id__":1},"asset":{"__uuid__":"b4a7SA5XNNRKz93p7VvlYs"},"fileId":"5072cnBQXhHF4jqXPch96WR"},"_contentSize":{"__type__":"cc.Size","width":100,"height":40}}],{"__type__":"cc.SpriteFrame","content":{"name":"default_btn_pressed","texture":"b4P/PCArtIdIH38t6mlw8Y","rect":[0,0,40,40],"offset":[0,0],"originalSize":[40,40],"capInsets":[11,11,11,7]}}]