[{"__type__":"cc.SpriteFrame","content":{"name":"jetton_num","texture":"182ea7283","rect":[390,93,120,17],"offset":[0,0],"originalSize":[120,17]}},{"__type__":"cc.LabelAtlas","_name":"Jetton_NumAtlas","spriteFrame":{"__uuid__":"bd4z5FVKJKk73NiWwT9lv1"},"fontSize":14.96,"_fntConfig":{"commonHeight":17,"fontSize":14,"atlasName":"jetton_num","fontDefDictionary":{"48":{"rect":{"x":0,"y":0,"width":12,"height":17},"xOffset":0,"yOffset":0,"xAdvance":12},"49":{"rect":{"x":12,"y":0,"width":12,"height":17},"xOffset":0,"yOffset":0,"xAdvance":12},"50":{"rect":{"x":24,"y":0,"width":12,"height":17},"xOffset":0,"yOffset":0,"xAdvance":12},"51":{"rect":{"x":36,"y":0,"width":12,"height":17},"xOffset":0,"yOffset":0,"xAdvance":12},"52":{"rect":{"x":48,"y":0,"width":12,"height":17},"xOffset":0,"yOffset":0,"xAdvance":12},"53":{"rect":{"x":60,"y":0,"width":12,"height":17},"xOffset":0,"yOffset":0,"xAdvance":12},"54":{"rect":{"x":72,"y":0,"width":12,"height":17},"xOffset":0,"yOffset":0,"xAdvance":12},"55":{"rect":{"x":84,"y":0,"width":12,"height":17},"xOffset":0,"yOffset":0,"xAdvance":12},"56":{"rect":{"x":96,"y":0,"width":12,"height":17},"xOffset":0,"yOffset":0,"xAdvance":12},"57":{"rect":{"x":108,"y":0,"width":12,"height":17},"xOffset":0,"yOffset":0,"xAdvance":12}},"kerningDict":{}}}]